aiidalab_qe/__init__.py
aiidalab_qe/__main__.py
aiidalab_qe/utils.py
aiidalab_qe/version.py
aiidalab_qe/app/__init__.py
aiidalab_qe/app/main.py
aiidalab_qe/app/wizard_app.py
aiidalab_qe/app/wrapper.py
aiidalab_qe/app/configuration/__init__.py
aiidalab_qe/app/configuration/model.py
aiidalab_qe/app/configuration/advanced/__init__.py
aiidalab_qe/app/configuration/advanced/advanced.py
aiidalab_qe/app/configuration/advanced/model.py
aiidalab_qe/app/configuration/advanced/subsettings.py
aiidalab_qe/app/configuration/advanced/hubbard/__init__.py
aiidalab_qe/app/configuration/advanced/hubbard/hubbard.py
aiidalab_qe/app/configuration/advanced/hubbard/model.py
aiidalab_qe/app/configuration/advanced/magnetization/__init__.py
aiidalab_qe/app/configuration/advanced/magnetization/magnetization.py
aiidalab_qe/app/configuration/advanced/magnetization/model.py
aiidalab_qe/app/configuration/advanced/pseudos/__init__.py
aiidalab_qe/app/configuration/advanced/pseudos/model.py
aiidalab_qe/app/configuration/advanced/pseudos/pseudos.py
aiidalab_qe/app/configuration/advanced/smearing/__init__.py
aiidalab_qe/app/configuration/advanced/smearing/model.py
aiidalab_qe/app/configuration/advanced/smearing/smearing.py
aiidalab_qe/app/configuration/basic/__init__.py
aiidalab_qe/app/configuration/basic/basic.py
aiidalab_qe/app/configuration/basic/model.py
aiidalab_qe/app/parameters/__init__.py
aiidalab_qe/app/parameters/qeapp.yaml
aiidalab_qe/app/result/__init__.py
aiidalab_qe/app/result/model.py
aiidalab_qe/app/result/components/__init__.py
aiidalab_qe/app/result/components/status/__init__.py
aiidalab_qe/app/result/components/status/model.py
aiidalab_qe/app/result/components/status/status.py
aiidalab_qe/app/result/components/summary/__init__.py
aiidalab_qe/app/result/components/summary/download_data.py
aiidalab_qe/app/result/components/summary/model.py
aiidalab_qe/app/result/components/summary/outputs.py
aiidalab_qe/app/result/components/summary/schema.json
aiidalab_qe-25.3.0.dist-info/LICENSE
aiidalab_qe-25.3.0.dist-info/METADATA
aiidalab_qe-25.3.0.dist-info/WHEEL
aiidalab_qe-25.3.0.dist-info/entry_points.txt
aiidalab_qe-25.3.0.dist-info/top_level.txt
aiidalab_qe-25.3.0.dist-info/RECORD
