Metadata-Version: 2.2
Name: aiidalab_qe
Version: 25.3.0
Summary: Package for the AiiDAlab QE app
Home-page: https://github.com/aiidalab/aiidalab-qe
Author: AiiDAlab team
Author-email: aiidalab@materialscloud.org
License: MIT
Project-URL: Bug Tracker, https://github.com/aiidalab/aiidalab-qe/issues
Project-URL: Documentation, https://aiidalab-qe.readthedocs.io/
Project-URL: Logo, https://raw.githubusercontent.com/aiidalab/aiidalab-qe/master/miscellaneous/logos/QE.jpg
Classifier: License :: OSI Approved :: MIT License
Classifier: Operating System :: OS Independent
Classifier: Programming Language :: Python :: 3
Classifier: Programming Language :: Python :: 3 :: Only
Requires-Python: >=3.9
License-File: LICENSE
Requires-Dist: aiida-core<3,~=2.5
Requires-Dist: Jinja2~=3.0
Requires-Dist: aiida-quantumespresso~=4.9
Requires-Dist: aiidalab-widgets-base[optimade]~=2.4.0
Requires-Dist: aiida-pseudo~=1.4
Requires-Dist: filelock~=3.8
Requires-Dist: importlib-resources~=5.2
Requires-Dist: aiida-wannier90-workflows==2.3.0
Requires-Dist: anywidget==0.9.13
Requires-Dist: table_widget~=0.0.2
Requires-Dist: shakenbreak~=3.3.1
Requires-Dist: plotly~=5.24
Provides-Extra: dev
Requires-Dist: bumpver~=2023.1124; extra == "dev"
Requires-Dist: pre-commit~=3.2; extra == "dev"
Requires-Dist: pytest~=7.4; extra == "dev"
Requires-Dist: pytest-regressions~=2.2; extra == "dev"
Requires-Dist: pgtest==1.3.1; extra == "dev"
Requires-Dist: pytest-cov~=5.0; extra == "dev"
